flasgger_marshmallow/__init__.py
flasgger_marshmallow-0.0.1.dist-info/LICENSE
flasgger_marshmallow-0.0.1.dist-info/METADATA
flasgger_marshmallow-0.0.1.dist-info/WHEEL
flasgger_marshmallow-0.0.1.dist-info/top_level.txt
flasgger_marshmallow-0.0.1.dist-info/zip-safe
flasgger_marshmallow-0.0.1.dist-info/RECORD
