Metadata-Version: 2.1
Name: flasgger-marshmallow
Version: 0.0.1
Summary: code to swagger document.
Home-page: https://github.com/flask-rabmq/Flasgger-Marshmallow
Author: chenxiaolong
Author-email: cxiaolong6@gmail.com
License: MIT
Keywords: python flask swagger flasgger marshmallow restfull
Platform: UNKNOWN
Classifier: License :: OSI Approved :: MIT License
Classifier: Programming Language :: Python
Classifier: Intended Audience :: Developers
Classifier: Operating System :: OS Independent
Requires-Python: >=2.7, !=3.0.*, !=3.1.*, !=3.2.*, !=3.3.*, !=3.4.*, !=3.5.*
Requires-Dist: flask (>=1.0.0)
Requires-Dist: flasgger (>=0.9.3)
Requires-Dist: marshmallow (>=2.18.1)
Requires-Dist: PyYAML
